supertabnanny/__init__.py
supertabnanny/__main__.py
supertabnanny/console.py
supertabnanny/frontend.py
supertabnanny/parser.py
supertabnanny/py.typed
supertabnanny/whitespace.py
supertabnanny-0.1.1.dist-info/METADATA
supertabnanny-0.1.1.dist-info/WHEEL
supertabnanny-0.1.1.dist-info/entry_points.txt
supertabnanny-0.1.1.dist-info/top_level.txt
supertabnanny-0.1.1.dist-info/RECORD
