Metadata-Version: 2.2
Name: supertabnanny
Version: 0.1.1
Summary: Super Tab Nanny - an inofficial rewrite
Author-email: Rainer Schwarzbach <rainer@blackstream.de>
License: MIT License
Project-URL: Homepage, https://gitlab.com/blackstream-x/supertabnanny
Project-URL: CI, https://gitlab.com/blackstream-x/supertabnanny/-/pipelines
Project-URL: Bug Tracker, https://gitlab.com/blackstream-x/supertabnanny/-/issues
Project-URL: Repository, https://gitlab.com/blackstream-x/supertabnanny.git
Keywords: tab,nanny
Classifier: Development Status :: 4 - Beta
Classifier: License :: OSI Approved :: MIT License
Classifier: Operating System :: OS Independent
Classifier: Programming Language :: Python :: 3
Classifier: Programming Language :: Python :: 3.10
Classifier: Programming Language :: Python :: 3.11
Classifier: Programming Language :: Python :: 3.12
Classifier: Programming Language :: Python :: 3.13
Classifier: Programming Language :: Python :: 3 :: Only
Classifier: Topic :: Software Development :: Libraries :: Python Modules
Classifier: Intended Audience :: Developers
Requires-Python: >=3.10
